{
  "lastUpdated": "2026-06-05T19:02:52.326Z",
  "news": [
    {
      "id": "news-0",
      "headline": "Death of girl, 11, in France sparks storm over cracks in judicial system",
      "summary": "A firestorm of recrimination raged in France on Friday over failures in the justice system that kept a man now suspected in the disappearance and death of an 11-year-old girl out of custody despite allegations that he preyed on young adolescents.\nThe disappearance of the girl identified by police as",
      "urgency": "info",
      "topic": "general",
      "sources": [
        {
          "name": "SCMP",
          "logo": "https://www.google.com/s2/favicons?domain=scmp.com&sz=32",
          "url": "https://scmp.com",
          "category": "local_media"
        }
      ],
      "timestamp": "2026-06-05T19:01:20.000Z",
      "widgetType": "news",
      "link": "https://www.scmp.com/news/world/europe/article/3356177/death-girl-11-france-sparks-storm-over-cracks-judicial-system?utm_source=rss_feed"
    },
    {
      "id": "news-1",
      "headline": "Govt reduces petrol price by Rs4, keeps diesel price unchanged",
      "summary": "&lt;p&gt;The government on Friday cut the petrol price by Rs4 per litre and kept the diesel rate unchanged with immediate effect for the week ending June 12, owing to changes in global prices over the past week.&lt;/p&gt;\n&lt;p&gt;Accordingly, the ex-depot price of high-speed diesel (HSD) will remai",
      "urgency": "important",
      "topic": "general",
      "sources": [
        {
          "name": "Dawn",
          "logo": "https://www.google.com/s2/favicons?domain=dawn.com&sz=32",
          "url": "https://dawn.com",
          "category": "local_media"
        }
      ],
      "timestamp": "2026-06-05T19:01:02.000Z",
      "widgetType": "news",
      "link": "https://www.dawn.com/news/2005447/govt-reduces-petrol-price-by-rs4-keeps-diesel-price-unchanged"
    },
    {
      "id": "news-2",
      "headline": "Trump says he wants his new acting director of national intelligence to cut the office",
      "summary": "Trump says he wants his new acting director of national intelligence to cut the office",
      "urgency": "info",
      "topic": "general",
      "sources": [
        {
          "name": "Gulf News",
          "logo": "https://www.google.com/s2/favicons?domain=gulfnews.com&sz=32",
          "url": "https://gulfnews.com",
          "category": "local_media"
        }
      ],
      "timestamp": "2026-06-05T18:54:58.000Z",
      "widgetType": "news",
      "link": "https://gulfnews.com/world/americas/trump-says-he-wants-his-new-acting-director-of-national-intelligence-to-cut-the-office-1.500565003"
    },
    {
      "id": "news-3",
      "headline": "AJK govt bans Joint Awami Action Committee under Anti-Terrorism Act",
      "summary": "&lt;p&gt;The government of Azad Jammu and Kashmir on Friday declared the Joint Awami Action Committee (JAAC) a proscribed organisation and placed it under the First Schedule of the region’s Anti-Terrorism Act 2014.&lt;/p&gt;\n&lt;p&gt;The notification by AJK’s Home Department said the group is “engag",
      "urgency": "breaking",
      "topic": "general",
      "sources": [
        {
          "name": "Dawn",
          "logo": "https://www.google.com/s2/favicons?domain=dawn.com&sz=32",
          "url": "https://dawn.com",
          "category": "local_media"
        }
      ],
      "timestamp": "2026-06-05T18:50:09.000Z",
      "widgetType": "news",
      "link": "https://www.dawn.com/news/2005462/ajk-govt-bans-joint-awami-action-committee-under-anti-terrorism-act"
    },
    {
      "id": "news-4",
      "headline": "Is the latest US ceasefire deal for Lebanon meaningless?",
      "summary": "Israel and Hezbollah continue fighting after truce announcement.",
      "urgency": "breaking",
      "topic": "general",
      "sources": [
        {
          "name": "Al Jazeera",
          "logo": "https://www.google.com/s2/favicons?domain=aljazeera.com&sz=32",
          "url": "https://aljazeera.com",
          "category": "global_media"
        }
      ],
      "timestamp": "2026-06-05T18:45:16.000Z",
      "widgetType": "news",
      "link": "https://www.aljazeera.com/video/inside-story/2026/6/5/is-the-latest-us-ceasefire-deal-for-lebanon-meaningless?traffic_source=rss"
    },
    {
      "id": "news-5",
      "headline": "Epstein's prison guard reveals shocking details about day he was found dead in his cell",
      "summary": "&lt;img border=\"0\" hspace=\"10\" align=\"left\" style=\"margin-top:3px;margin-right:5px;\" src=\"https://timesofindia.indiatimes.com/photo/131536340.cms\" /&gt;<![CDATA[",
      "urgency": "breaking",
      "topic": "general",
      "sources": [
        {
          "name": "Times of India",
          "logo": "https://www.google.com/s2/favicons?domain=timesofindia.indiatimes.com&sz=32",
          "url": "https://timesofindia.indiatimes.com",
          "category": "local_media"
        }
      ],
      "timestamp": "2026-06-05T18:41:01.000Z",
      "widgetType": "news",
      "link": "https://timesofindia.indiatimes.com/world/us/epsteins-prison-guard-reveals-shocking-details-about-day-convicted-pedophile-was-found-dead-in-his-cell-to-be-very-honest-/articleshow/131536340.cms"
    },
    {
      "id": "news-6",
      "headline": "UN Envoy sees regional consensus as key to swift Middle East conflict resolution",
      "summary": "UN Envoy sees regional consensus as key to swift Middle East conflict resolution",
      "urgency": "info",
      "topic": "middle-east",
      "sources": [
        {
          "name": "Gulf News",
          "logo": "https://www.google.com/s2/favicons?domain=gulfnews.com&sz=32",
          "url": "https://gulfnews.com",
          "category": "local_media"
        }
      ],
      "timestamp": "2026-06-05T18:40:22.000Z",
      "widgetType": "news",
      "link": "https://gulfnews.com/uae/c0kmby0-envoy-sees-regional-consensus-key-swift-middle-1.500564990"
    },
    {
      "id": "news-7",
      "headline": "Huge fire erupts at Honda warehouse in Barcelona",
      "summary": "Around 150 workers were evacuated after a fire broke out at a Honda industrial warehouse in Barcelona.",
      "urgency": "breaking",
      "topic": "general",
      "sources": [
        {
          "name": "Al Jazeera",
          "logo": "https://www.google.com/s2/favicons?domain=aljazeera.com&sz=32",
          "url": "https://aljazeera.com",
          "category": "global_media"
        }
      ],
      "timestamp": "2026-06-05T18:39:12.000Z",
      "widgetType": "news",
      "link": "https://www.aljazeera.com/video/newsfeed/2026/6/5/huge-fire-erupts-at-honda-warehouse-in-barcelona?traffic_source=rss"
    },
    {
      "id": "news-8",
      "headline": "UAE mediates exchange of 370 captives between Russia, Ukraine",
      "summary": "Latest UAE mediation efforts succeed in exchange of 370 captives between Russia and Ukraine",
      "urgency": "info",
      "topic": "ukraine-russia",
      "sources": [
        {
          "name": "Gulf News",
          "logo": "https://www.google.com/s2/favicons?domain=gulfnews.com&sz=32",
          "url": "https://gulfnews.com",
          "category": "local_media"
        }
      ],
      "timestamp": "2026-06-05T18:34:57.000Z",
      "widgetType": "news",
      "link": "https://gulfnews.com/uae/latest-uae-mediation-efforts-succeed-in-exchange-of-370-captives-between-russia-and-ukraine-1.500564927"
    },
    {
      "id": "news-9",
      "headline": "Why Ivanka’s Albanian Dream is a Protestors Nightmare",
      "summary": "Erisa Kryeziu is an Albanian journalist for the independent media outlet Citizens.AL, based in Albania.",
      "urgency": "important",
      "topic": "general",
      "sources": [
        {
          "name": "France 24",
          "logo": "https://www.google.com/s2/favicons?domain=france24.com&sz=32",
          "url": "https://france24.com",
          "category": "global_media"
        }
      ],
      "timestamp": "2026-06-05T18:32:31.000Z",
      "widgetType": "news",
      "link": "https://www.france24.com/en/tv-shows/spotlight/20260605-why-ivanka-s-albanian-dream-is-a-protestors-nightmare"
    },
    {
      "id": "news-10",
      "headline": "Ukraine: Dear Putin, Lebanon: A Crude Call, Colombia's 'Tiger'",
      "summary": "In a week where a renewed ceasefire was proclaimed between Israel and Lebanon, a deal that hinges on the complete cessation of attacks from the Iranian backed militants Hezbollah and withdrawal from the south of the country.",
      "urgency": "breaking",
      "topic": "ukraine-russia",
      "sources": [
        {
          "name": "France 24",
          "logo": "https://www.google.com/s2/favicons?domain=france24.com&sz=32",
          "url": "https://france24.com",
          "category": "global_media"
        }
      ],
      "timestamp": "2026-06-05T18:26:45.000Z",
      "widgetType": "news",
      "link": "https://www.france24.com/en/tv-shows/the-world-this-week/20260605-ukraine-dear-putin-lebanon-a-crude-call-colombia-s-tiger"
    },
    {
      "id": "news-11",
      "headline": "Putin says there is 'no point' meeting Zelensky over ending Ukraine war",
      "summary": "The Russian president's refusal comes after his Ukrainian counterpart wrote an open letter calling for face-to-face talks.",
      "urgency": "breaking",
      "topic": "ukraine-russia",
      "sources": [
        {
          "name": "BBC World",
          "logo": "https://www.google.com/s2/favicons?domain=bbc.com&sz=32",
          "url": "https://bbc.com/news",
          "category": "global_media"
        }
      ],
      "timestamp": "2026-06-05T18:16:15.000Z",
      "widgetType": "news",
      "link": "https://www.bbc.com/news/articles/cpqpqx5qe40o?at_medium=RSS&amp;at_campaign=rss"
    },
    {
      "id": "news-12",
      "headline": "Singer Fally Ipupa's pride at being given major DR Congo honour",
      "summary": "He follows the late great Papa Wemba in becoming a knight of the National Order of the Leopard.",
      "urgency": "info",
      "topic": "general",
      "sources": [
        {
          "name": "BBC World",
          "logo": "https://www.google.com/s2/favicons?domain=bbc.com&sz=32",
          "url": "https://bbc.com/news",
          "category": "global_media"
        }
      ],
      "timestamp": "2026-06-05T18:15:42.000Z",
      "widgetType": "news",
      "link": "https://www.bbc.com/news/articles/clypyd6gj72o?at_medium=RSS&amp;at_campaign=rss"
    },
    {
      "id": "news-13",
      "headline": "ISS leak prompts astronauts to shelter in Dragon capsule",
      "summary": "ISS leak prompts astronauts to shelter in Dragon capsule",
      "urgency": "info",
      "topic": "general",
      "sources": [
        {
          "name": "Gulf News",
          "logo": "https://www.google.com/s2/favicons?domain=gulfnews.com&sz=32",
          "url": "https://gulfnews.com",
          "category": "local_media"
        }
      ],
      "timestamp": "2026-06-05T18:15:11.000Z",
      "widgetType": "news",
      "link": "https://gulfnews.com/world/americas/iss-leak-prompts-astronauts-to-shelter-in-dragon-capsule-1.500564977"
    },
    {
      "id": "news-14",
      "headline": "Trump admin’s cancellation of wind energy projects causes business turmoil",
      "summary": "Seven northeastern states have sued US gov&#039;t for paying TotalEnergies to withdraw from offshore wind projects.",
      "urgency": "info",
      "topic": "general",
      "sources": [
        {
          "name": "Al Jazeera",
          "logo": "https://www.google.com/s2/favicons?domain=aljazeera.com&sz=32",
          "url": "https://aljazeera.com",
          "category": "global_media"
        }
      ],
      "timestamp": "2026-06-05T18:12:44.000Z",
      "widgetType": "news",
      "link": "https://www.aljazeera.com/economy/2026/6/5/trump-admins-cancellation-of-wind-energy-projects-causes-business-turmoil?traffic_source=rss"
    },
    {
      "id": "news-15",
      "headline": "First AI-designed ‘universal vaccine’ tested in humans",
      "summary": "A vaccine targeting a broad range of viruses that was designed using artificial intelligence had a “modest” effect on immune systems in a small, early trial, according to a new study.\nThe trial marks the first time a vaccine whose active ingredient was entirely designed by AI has been tested in huma",
      "urgency": "info",
      "topic": "general",
      "sources": [
        {
          "name": "SCMP",
          "logo": "https://www.google.com/s2/favicons?domain=scmp.com&sz=32",
          "url": "https://scmp.com",
          "category": "local_media"
        }
      ],
      "timestamp": "2026-06-05T18:12:34.000Z",
      "widgetType": "news",
      "link": "https://www.scmp.com/news/world/europe/article/3356176/first-ai-designed-universal-vaccine-tested-humans?utm_source=rss_feed"
    },
    {
      "id": "news-16",
      "headline": "Earthquake tremors felt in Lahore, other parts of Punjab: PDMA",
      "summary": "&lt;p&gt;Tremors were felt in Lahore and other districts of Punjab on Friday after a 4.9-magnitude earthquake was reported, said a statement by the Punjab Disaster Management Authority (PDMA).&lt;/p&gt;\n&lt;p&gt;A PDMA spokesperson said the depth of the earthquake was recorded at 18 kilometres, whil",
      "urgency": "breaking",
      "topic": "general",
      "sources": [
        {
          "name": "Dawn",
          "logo": "https://www.google.com/s2/favicons?domain=dawn.com&sz=32",
          "url": "https://dawn.com",
          "category": "local_media"
        }
      ],
      "timestamp": "2026-06-05T18:10:54.000Z",
      "widgetType": "news",
      "link": "https://www.dawn.com/news/2005458/earthquake-tremors-felt-in-lahore-other-parts-of-punjab-pdma"
    },
    {
      "id": "news-17",
      "headline": "Russia’s Putin says ‘no point’ meeting Ukraine’s Zelenskyy for now",
      "summary": "The Russian leader insisted military action would only stop after Moscow achieves its &#039;goals&#039;.",
      "urgency": "info",
      "topic": "ukraine-russia",
      "sources": [
        {
          "name": "Al Jazeera",
          "logo": "https://www.google.com/s2/favicons?domain=aljazeera.com&sz=32",
          "url": "https://aljazeera.com",
          "category": "global_media"
        }
      ],
      "timestamp": "2026-06-05T18:04:27.000Z",
      "widgetType": "news",
      "link": "https://www.aljazeera.com/news/2026/6/5/russias-putin-says-no-point-meeting-ukraines-zelenskyy-for-now?traffic_source=rss"
    },
    {
      "id": "news-18",
      "headline": "Election campaigning ends in GB as 48-hour ban comes into force",
      "summary": "&lt;p&gt;The Gilgit-Baltistan Election Commission on Friday announced the end of election campaigning 48 hours before polling day, prohibiting all election-related activities in the region, according to a press release.&lt;/p&gt;\n&lt;p&gt;The general elections for the GB’s legislative assembly are &",
      "urgency": "breaking",
      "topic": "general",
      "sources": [
        {
          "name": "Dawn",
          "logo": "https://www.google.com/s2/favicons?domain=dawn.com&sz=32",
          "url": "https://dawn.com",
          "category": "local_media"
        }
      ],
      "timestamp": "2026-06-05T17:58:57.000Z",
      "widgetType": "news",
      "link": "https://www.dawn.com/news/2005451/election-campaigning-ends-in-gb-as-48-hour-ban-comes-into-force"
    },
    {
      "id": "news-19",
      "headline": "Henry Nowak won't be the last: JD Vance blames mass migration for UK stabbing, triggers diplomatic row",
      "summary": "&lt;img border=\"0\" hspace=\"10\" align=\"left\" style=\"margin-top:3px;margin-right:5px;\" src=\"https://timesofindia.indiatimes.com/photo/131538491.cms\" /&gt;<![CDATA[",
      "urgency": "info",
      "topic": "general",
      "sources": [
        {
          "name": "Times of India",
          "logo": "https://www.google.com/s2/favicons?domain=timesofindia.indiatimes.com&sz=32",
          "url": "https://timesofindia.indiatimes.com",
          "category": "local_media"
        }
      ],
      "timestamp": "2026-06-05T17:56:21.000Z",
      "widgetType": "news",
      "link": "https://timesofindia.indiatimes.com/world/us/henry-nowak-wont-be-the-last-jd-vance-blames-mass-migration-for-uk-stabbing-triggers-diplomatic-row/articleshow/131538491.cms"
    },
    {
      "id": "news-20",
      "headline": "Ukraine and Russia exchange 185 prisoners of war each",
      "summary": "Russia and Ukraine have each released 185 prisoners in a major exchange, which Russia says was mediated by the UAE.",
      "urgency": "breaking",
      "topic": "ukraine-russia",
      "sources": [
        {
          "name": "Al Jazeera",
          "logo": "https://www.google.com/s2/favicons?domain=aljazeera.com&sz=32",
          "url": "https://aljazeera.com",
          "category": "global_media"
        }
      ],
      "timestamp": "2026-06-05T17:54:01.000Z",
      "widgetType": "news",
      "link": "https://www.aljazeera.com/video/newsfeed/2026/6/5/ukraine-and-russia-exchange-185-prisoners-of-war-each?traffic_source=rss"
    },
    {
      "id": "news-21",
      "headline": "Video shows moment Israeli air strike hits car in southern Lebanon",
      "summary": "Video shows the moment when journalist Abbas Fakih was reporting in Nabatieh, Lebanon and an Israeli air strike hit.",
      "urgency": "breaking",
      "topic": "middle-east",
      "sources": [
        {
          "name": "Al Jazeera",
          "logo": "https://www.google.com/s2/favicons?domain=aljazeera.com&sz=32",
          "url": "https://aljazeera.com",
          "category": "global_media"
        }
      ],
      "timestamp": "2026-06-05T17:44:52.000Z",
      "widgetType": "news",
      "link": "https://www.aljazeera.com/video/newsfeed/2026/6/5/video-shows-moment-israeli-air-strike-hits-car-in-southern-lebanon?traffic_source=rss"
    },
    {
      "id": "news-22",
      "headline": "CBSE extends deadline for Class 12 verification and re-evaluation applications",
      "summary": "CBSE extends deadline for Class 12 verification and re-evaluation applications",
      "urgency": "breaking",
      "topic": "general",
      "sources": [
        {
          "name": "Gulf News",
          "logo": "https://www.google.com/s2/favicons?domain=gulfnews.com&sz=32",
          "url": "https://gulfnews.com",
          "category": "local_media"
        }
      ],
      "timestamp": "2026-06-05T17:44:23.000Z",
      "widgetType": "news",
      "link": "https://gulfnews.com/uae/education/cbse-extends-deadline-for-class-12-verification-and-re-evaluation-applications-1.500564950"
    },
    {
      "id": "news-23",
      "headline": "A Question Swirling Around Putin’s Big Conference: Could the War End?",
      "summary": "At the St. Petersburg economic forum, business and political elites said Russia faced a choice of halting the conflict or sacrificing more. Vladimir Putin seemed to signal more war.",
      "urgency": "breaking",
      "topic": "ukraine-russia",
      "sources": [
        {
          "name": "NY Times",
          "logo": "https://www.google.com/s2/favicons?domain=nytimes.com&sz=32",
          "url": "https://nytimes.com",
          "category": "global_media"
        }
      ],
      "timestamp": "2026-06-05T17:41:02.000Z",
      "widgetType": "news",
      "link": "https://www.nytimes.com/2026/06/05/world/europe/putin-war-st-petersburg-economic-forum.html"
    },
    {
      "id": "news-24",
      "headline": "Germany’s Merz says EU to initiate integration of Western Balkans",
      "summary": "Alongside Ukraine and Moldova, six Western Balkan nations wish to join the European Union.",
      "urgency": "info",
      "topic": "general",
      "sources": [
        {
          "name": "Al Jazeera",
          "logo": "https://www.google.com/s2/favicons?domain=aljazeera.com&sz=32",
          "url": "https://aljazeera.com",
          "category": "global_media"
        }
      ],
      "timestamp": "2026-06-05T17:40:07.000Z",
      "widgetType": "news",
      "link": "https://www.aljazeera.com/news/2026/6/5/germanys-merz-says-eu-to-initiate-integration-of-western-balkans?traffic_source=rss"
    },
    {
      "id": "news-25",
      "headline": "Washington National Guard Builds Counter-UAS Partnerships Ahead of World Cup 2026",
      "summary": "As unmanned aerial systems continue to evolve from recreational tools into potential threats to public safety, critical infrastructure and major public events, the Washington National Guard is positioning itself at the forefront of counter-UAS training and readiness.",
      "urgency": "info",
      "topic": "general",
      "sources": [
        {
          "name": "US Pentagon",
          "logo": "https://www.google.com/s2/favicons?domain=defense.gov&sz=32",
          "url": "https://defense.gov",
          "category": "government"
        }
      ],
      "timestamp": "2026-06-05T17:36:33.000Z",
      "widgetType": "news",
      "link": "https://www.war.gov/News/News-Stories/Article/Article/4509924/washington-national-guard-builds-counter-uas-partnerships-ahead-of-world-cup-20/"
    },
    {
      "id": "news-26",
      "headline": "Lawsuit challenges US ‘third-country’ deportations to Equatorial Guinea",
      "summary": "Complaint filed to African Commission on Human and Peoples&#039; Rights challenges controversial expulsion practice.",
      "urgency": "info",
      "topic": "general",
      "sources": [
        {
          "name": "Al Jazeera",
          "logo": "https://www.google.com/s2/favicons?domain=aljazeera.com&sz=32",
          "url": "https://aljazeera.com",
          "category": "global_media"
        }
      ],
      "timestamp": "2026-06-05T17:35:36.000Z",
      "widgetType": "news",
      "link": "https://www.aljazeera.com/news/2026/6/5/lawsuit-challenges-us-third-country-deportations-to-equatorial-guinea?traffic_source=rss"
    },
    {
      "id": "news-27",
      "headline": "Iran World Cup players granted US visas: White House",
      "summary": "Iran World Cup players granted US visas: White House",
      "urgency": "info",
      "topic": "middle-east",
      "sources": [
        {
          "name": "Gulf News",
          "logo": "https://www.google.com/s2/favicons?domain=gulfnews.com&sz=32",
          "url": "https://gulfnews.com",
          "category": "local_media"
        }
      ],
      "timestamp": "2026-06-05T17:32:14.000Z",
      "widgetType": "news",
      "link": "https://gulfnews.com/world/mena/iran-world-cup-players-granted-us-visas-white-house-1.500564939"
    },
    {
      "id": "news-28",
      "headline": "US judge strikes down Trump policies targeting immigrants from 39 countries",
      "summary": "President Donald ⁠Trump’s administration unlawfully barred applicants from ⁠39 travel-ban countries from receiving decisions on asylum, work permits, green cards and citizenship, a US federal judge ruled on Friday.\nChief US District Judge John McConnell in Providence, Rhode Island, ruled that the US",
      "urgency": "breaking",
      "topic": "general",
      "sources": [
        {
          "name": "SCMP",
          "logo": "https://www.google.com/s2/favicons?domain=scmp.com&sz=32",
          "url": "https://scmp.com",
          "category": "local_media"
        }
      ],
      "timestamp": "2026-06-05T17:28:59.000Z",
      "widgetType": "news",
      "link": "https://www.scmp.com/news/world/united-states-canada/article/3356175/us-judge-strikes-down-trump-policies-targeting-immigrants-39-countries?utm_source=rss_feed"
    },
    {
      "id": "news-29",
      "headline": "French diplomat in Mali sentenced to 20 years in prison for 'undermining state security'",
      "summary": "A court in Mali has sentenced a French intelligence agent with diplomatic status to 20 years in prison for “undermining state security”, judicial sources said Friday, in a ruling that further strains already fraught relations between the West African junta-led state and its former colonial ruler Fra",
      "urgency": "info",
      "topic": "general",
      "sources": [
        {
          "name": "France 24",
          "logo": "https://www.google.com/s2/favicons?domain=france24.com&sz=32",
          "url": "https://france24.com",
          "category": "global_media"
        }
      ],
      "timestamp": "2026-06-05T17:28:54.000Z",
      "widgetType": "news",
      "link": "https://www.france24.com/en/africa/20260605-french-diplomat-in-mali-sentenced-to-20-years-in-prison-for-undermining-state-security"
    },
    {
      "id": "news-30",
      "headline": "An ice cream parlour survives Gaza’s genocide and gives seven students hope",
      "summary": "Gaza medical and dental students sell ice cream in Khan Younis to fund their studies and keep their dreams alive",
      "urgency": "breaking",
      "topic": "middle-east",
      "sources": [
        {
          "name": "Al Jazeera",
          "logo": "https://www.google.com/s2/favicons?domain=aljazeera.com&sz=32",
          "url": "https://aljazeera.com",
          "category": "global_media"
        }
      ],
      "timestamp": "2026-06-05T17:25:06.000Z",
      "widgetType": "news",
      "link": "https://www.aljazeera.com/news/2026/6/5/an-ice-cream-parlour-survives-gazas-genocide-and-gives-seven-students-hope?traffic_source=rss"
    },
    {
      "id": "news-31",
      "headline": "Buffy the Vampire Slayer, Ted Lasso actor Anthony Head dies aged 72",
      "summary": "Actor Anthony Head, best known for his roles in Buffy The Vampire Slayer and Ted Lasso, has died at the age of 72, his family announced on Friday.\nThe British actor, the brother of singer Murray Head, was best known as librarian Rupert Giles in the cult US supernatural television series starring Sar",
      "urgency": "info",
      "topic": "general",
      "sources": [
        {
          "name": "SCMP",
          "logo": "https://www.google.com/s2/favicons?domain=scmp.com&sz=32",
          "url": "https://scmp.com",
          "category": "local_media"
        }
      ],
      "timestamp": "2026-06-05T17:14:55.000Z",
      "widgetType": "news",
      "link": "https://www.scmp.com/news/world/united-states-canada/article/3356174/buffy-vampire-slayer-ted-lasso-actor-anthony-head-dies-aged-72?utm_source=rss_feed"
    },
    {
      "id": "news-32",
      "headline": "Russian Satellites Have Been Jamming GPS Signals Across Europe, Scientists Say",
      "summary": "Scientists and U.S. military briefers have linked short, widespread interference incidents to Russia, revealing vulnerabilities in a technology essential to everyday society.",
      "urgency": "info",
      "topic": "general",
      "sources": [
        {
          "name": "NY Times",
          "logo": "https://www.google.com/s2/favicons?domain=nytimes.com&sz=32",
          "url": "https://nytimes.com",
          "category": "global_media"
        }
      ],
      "timestamp": "2026-06-05T17:14:37.000Z",
      "widgetType": "news",
      "link": "https://www.nytimes.com/2026/06/05/world/europe/russia-satellites-gps-interference-europe.html"
    },
    {
      "id": "news-33",
      "headline": "Norway's crown princess on lung transplant waiting list, palace says",
      "summary": "Mette-Marit's condition, which stiffens the lungs, making it hard to breathe, has deteriorated, the royal household says.",
      "urgency": "info",
      "topic": "general",
      "sources": [
        {
          "name": "BBC World",
          "logo": "https://www.google.com/s2/favicons?domain=bbc.com&sz=32",
          "url": "https://bbc.com/news",
          "category": "global_media"
        }
      ],
      "timestamp": "2026-06-05T17:11:01.000Z",
      "widgetType": "news",
      "link": "https://www.bbc.com/news/articles/c9wewqxpq2eo?at_medium=RSS&amp;at_campaign=rss"
    },
    {
      "id": "news-34",
      "headline": "Pakistan ‘categorically rejects’ India’s remarks on GB elections as ‘baseless’",
      "summary": "&lt;p&gt;ISLAMABAD: Pakistan on Friday “categorically rejected” India’s remarks regarding upcoming elections in Gilgit-Baltistan (GB), calling them “baseless” and part of a “carefully choreographed attempt to conflate fact with fiction”.&lt;/p&gt;\n&lt;p&gt;General elections in GB are scheduled for S",
      "urgency": "important",
      "topic": "general",
      "sources": [
        {
          "name": "Dawn",
          "logo": "https://www.google.com/s2/favicons?domain=dawn.com&sz=32",
          "url": "https://dawn.com",
          "category": "local_media"
        }
      ],
      "timestamp": "2026-06-05T17:10:56.000Z",
      "widgetType": "news",
      "link": "https://www.dawn.com/news/2005452/pakistan-categorically-rejects-indias-remarks-on-gb-elections-as-baseless"
    },
    {
      "id": "news-35",
      "headline": "Maine Air National Guard Surges Support for Operation Epic Fury",
      "summary": "Air Transportation Function airmen assigned to the Maine Air National Guard's 101st Air Refueling Wing helped move more than 747,000 pounds of cargo and 312 passengers since the start of Operation Epic Fury.",
      "urgency": "info",
      "topic": "general",
      "sources": [
        {
          "name": "US Pentagon",
          "logo": "https://www.google.com/s2/favicons?domain=defense.gov&sz=32",
          "url": "https://defense.gov",
          "category": "government"
        }
      ],
      "timestamp": "2026-06-05T17:07:12.000Z",
      "widgetType": "news",
      "link": "https://www.war.gov/News/News-Stories/Article/Article/4509935/maine-air-national-guard-surges-support-for-operation-epic-fury/"
    },
    {
      "id": "news-36",
      "headline": "US judge invalidates travel and visa ban on 39 countries: What happens next?",
      "summary": "&lt;img border=\"0\" hspace=\"10\" align=\"left\" style=\"margin-top:3px;margin-right:5px;\" src=\"https://timesofindia.indiatimes.com/photo/131537140.cms\" /&gt;<![CDATA[",
      "urgency": "info",
      "topic": "general",
      "sources": [
        {
          "name": "Times of India",
          "logo": "https://www.google.com/s2/favicons?domain=timesofindia.indiatimes.com&sz=32",
          "url": "https://timesofindia.indiatimes.com",
          "category": "local_media"
        }
      ],
      "timestamp": "2026-06-05T17:06:25.000Z",
      "widgetType": "news",
      "link": "https://timesofindia.indiatimes.com/world/us/us-judge-invalidates-travel-and-visa-ban-on-39-countries-what-happens-next/articleshow/131537140.cms"
    },
    {
      "id": "news-37",
      "headline": "New US sanctions target Iran LPG and shadow banking system",
      "summary": "New US sanctions target Iran LPG and shadow banking system",
      "urgency": "important",
      "topic": "middle-east",
      "sources": [
        {
          "name": "Gulf News",
          "logo": "https://www.google.com/s2/favicons?domain=gulfnews.com&sz=32",
          "url": "https://gulfnews.com",
          "category": "local_media"
        }
      ],
      "timestamp": "2026-06-05T17:06:21.000Z",
      "widgetType": "news",
      "link": "https://gulfnews.com/world/mena/new-us-sanctions-target-iran-lpg-and-shadow-banking-system-1.500564905"
    },
    {
      "id": "news-38",
      "headline": "Somalia declares order restored after two days of fighting in Mogadishu",
      "summary": "Violence that paralysed two Mogadishu districts subsides, but opposition rejects president&#039;s rule and vows to fight on.",
      "urgency": "info",
      "topic": "general",
      "sources": [
        {
          "name": "Al Jazeera",
          "logo": "https://www.google.com/s2/favicons?domain=aljazeera.com&sz=32",
          "url": "https://aljazeera.com",
          "category": "global_media"
        }
      ],
      "timestamp": "2026-06-05T17:03:11.000Z",
      "widgetType": "news",
      "link": "https://www.aljazeera.com/news/2026/6/5/somalia-declares-order-restored-after-two-days-of-fighting-in-mogadishu?traffic_source=rss"
    },
    {
      "id": "news-39",
      "headline": "Astronauts take shelter as air leaks worsen on International Space Station",
      "summary": "A worsening air leak aboard the International Space Station prompted five astronauts to take shelter and prepare for evacuation for roughly two hours on Friday as Russia attempted to ‌fix a crack on its portion of the orbital laboratory, Nasa said.\nThe four astronauts of Nasa’s Crew-12 mission aboar",
      "urgency": "info",
      "topic": "general",
      "sources": [
        {
          "name": "SCMP",
          "logo": "https://www.google.com/s2/favicons?domain=scmp.com&sz=32",
          "url": "https://scmp.com",
          "category": "local_media"
        }
      ],
      "timestamp": "2026-06-05T16:57:45.000Z",
      "widgetType": "news",
      "link": "https://www.scmp.com/news/world/united-states-canada/article/3356173/astronauts-take-shelter-air-leaks-worsen-international-space-station?utm_source=rss_feed"
    },
    {
      "id": "news-40",
      "headline": "Ballistics Putin’s ‘last argument’ as Ukraine brings his army to standstill",
      "summary": "Russia’s performance since December shows it can contest territory but cannot hold it, say battlefield observers.",
      "urgency": "info",
      "topic": "ukraine-russia",
      "sources": [
        {
          "name": "Al Jazeera",
          "logo": "https://www.google.com/s2/favicons?domain=aljazeera.com&sz=32",
          "url": "https://aljazeera.com",
          "category": "global_media"
        }
      ],
      "timestamp": "2026-06-05T16:52:11.000Z",
      "widgetType": "news",
      "link": "https://www.aljazeera.com/news/2026/6/5/ballistics-putins-last-argument-as-ukraine-brings-his-army-to-standstill?traffic_source=rss"
    },
    {
      "id": "news-41",
      "headline": "France probes judicial 'dysfunction' after murder of 11‑year‑old Lyhanna shocks nation",
      "summary": "France probes judicial 'dysfunction' after murder of 11‑year‑old Lyhanna shocks nation",
      "urgency": "info",
      "topic": "general",
      "sources": [
        {
          "name": "France 24",
          "logo": "https://www.google.com/s2/favicons?domain=france24.com&sz=32",
          "url": "https://france24.com",
          "category": "global_media"
        }
      ],
      "timestamp": "2026-06-05T16:47:45.000Z",
      "widgetType": "news",
      "link": "https://www.france24.com/en/france/20260605-france-probes-judicial-dysfunction-after-suspected-murder-of-11%E2%80%91year%E2%80%91old-lyhanna"
    },
    {
      "id": "news-42",
      "headline": "Nasa reverses evacuation alert order for astronauts aboard International Space Station",
      "summary": "&lt;p&gt;A worsening air leak aboard the International Space Station (ISS) prompted five astronauts to take shelter and prepare for evacuation for roughly two hours on Friday as Russia attempted to fix a crack on its portion of the orbital laboratory, Nasa said.&lt;/p&gt;\n&lt;p&gt;The four astronaut",
      "urgency": "breaking",
      "topic": "general",
      "sources": [
        {
          "name": "Dawn",
          "logo": "https://www.google.com/s2/favicons?domain=dawn.com&sz=32",
          "url": "https://dawn.com",
          "category": "local_media"
        }
      ],
      "timestamp": "2026-06-05T16:47:33.000Z",
      "widgetType": "news",
      "link": "https://www.dawn.com/news/2005453/nasa-reverses-evacuation-alert-order-for-astronauts-aboard-international-space-station"
    },
    {
      "id": "news-43",
      "headline": "US Senate passes $70bn ICE funding bill: What comes next?",
      "summary": "Republicans pass key Trump initiative after marathon vote-a-rama, avoid barring controversial &#039;anti-weaponisation&#039; fund.",
      "urgency": "info",
      "topic": "general",
      "sources": [
        {
          "name": "Al Jazeera",
          "logo": "https://www.google.com/s2/favicons?domain=aljazeera.com&sz=32",
          "url": "https://aljazeera.com",
          "category": "global_media"
        }
      ],
      "timestamp": "2026-06-05T16:40:37.000Z",
      "widgetType": "news",
      "link": "https://www.aljazeera.com/news/2026/6/5/us-senate-passes-70bn-ice-funding-bill-what-comes-next?traffic_source=rss"
    },
    {
      "id": "news-44",
      "headline": "Indian student fights for life in Chicago after 25-ft fall at subway station, family seeks help",
      "summary": "&lt;img border=\"0\" hspace=\"10\" align=\"left\" style=\"margin-top:3px;margin-right:5px;\" src=\"https://timesofindia.indiatimes.com/photo/131536416.cms\" /&gt;<![CDATA[",
      "urgency": "info",
      "topic": "general",
      "sources": [
        {
          "name": "Times of India",
          "logo": "https://www.google.com/s2/favicons?domain=timesofindia.indiatimes.com&sz=32",
          "url": "https://timesofindia.indiatimes.com",
          "category": "local_media"
        }
      ],
      "timestamp": "2026-06-05T16:33:13.000Z",
      "widgetType": "news",
      "link": "https://timesofindia.indiatimes.com/world/us/indian-student-fights-for-life-in-chicago-after-25-ft-fall-at-subway-station-family-seeks-help/articleshow/131536416.cms"
    },
    {
      "id": "news-45",
      "headline": "Zverev cruises past Mensik to reach second French Open final",
      "summary": "Alexander Zverev will face either Flavio Cobolli or Matteo Arnaldi in final, after beating Jakub Mensik at French Open.",
      "urgency": "info",
      "topic": "general",
      "sources": [
        {
          "name": "Al Jazeera",
          "logo": "https://www.google.com/s2/favicons?domain=aljazeera.com&sz=32",
          "url": "https://aljazeera.com",
          "category": "global_media"
        }
      ],
      "timestamp": "2026-06-05T16:28:33.000Z",
      "widgetType": "news",
      "link": "https://www.aljazeera.com/sports/2026/6/5/zverev-cruises-past-mensik-to-reach-second-french-open-final?traffic_source=rss"
    },
    {
      "id": "news-46",
      "headline": "‘Gurdwara is empty’: Sikhs scared to come out of houses after Vickrum Digwa killed Henry Nowak",
      "summary": "&lt;img border=\"0\" hspace=\"10\" align=\"left\" style=\"margin-top:3px;margin-right:5px;\" src=\"https://timesofindia.indiatimes.com/photo/131535017.cms\" /&gt;<![CDATA[",
      "urgency": "breaking",
      "topic": "general",
      "sources": [
        {
          "name": "Times of India",
          "logo": "https://www.google.com/s2/favicons?domain=timesofindia.indiatimes.com&sz=32",
          "url": "https://timesofindia.indiatimes.com",
          "category": "local_media"
        }
      ],
      "timestamp": "2026-06-05T16:23:59.000Z",
      "widgetType": "news",
      "link": "https://timesofindia.indiatimes.com/world/uk/gurdwara-is-empty-sikhs-scared-to-come-out-of-houses-in-southampton-after-vickrum-digwa-killed-henry-nowak/articleshow/131535017.cms"
    },
    {
      "id": "news-47",
      "headline": "Why is Paris's oldest bridge called the 'New Bridge'?",
      "summary": "🌉 A runway for a Louis Vuitton show, covered entirely in fabric as part of two artistic installations, home to a now-demolished water pump... the oldest bridge in Paris, Pont Neuf, has seen it all. Why, then, does its name translate to \"New Bridge\"? FRANCE 24's Tanishk Saha explains.",
      "urgency": "info",
      "topic": "general",
      "sources": [
        {
          "name": "France 24",
          "logo": "https://www.google.com/s2/favicons?domain=france24.com&sz=32",
          "url": "https://france24.com",
          "category": "global_media"
        }
      ],
      "timestamp": "2026-06-05T16:16:58.000Z",
      "widgetType": "news",
      "link": "https://www.france24.com/en/video/20260605-why-is-paris-s-oldest-bridge-called-the-new-bridge"
    },
    {
      "id": "news-48",
      "headline": "Parisians will be able to swim for a second year in the Seine",
      "summary": "Parisians will once again be able to swim in the Seine this summer, city officials said Friday, building on the success of last year's historic reopening of the river after a century-long ban and a massive clean-up effort ahead of the 2024 Paris Olympics.",
      "urgency": "info",
      "topic": "general",
      "sources": [
        {
          "name": "France 24",
          "logo": "https://www.google.com/s2/favicons?domain=france24.com&sz=32",
          "url": "https://france24.com",
          "category": "global_media"
        }
      ],
      "timestamp": "2026-06-05T16:14:53.000Z",
      "widgetType": "news",
      "link": "https://www.france24.com/en/france/20260605-parisians-will-be-able-to-swim-for-a-second-year-in-the-seine-france"
    },
    {
      "id": "news-49",
      "headline": "Astronauts return to ISS after sheltering during air leak repair attempt",
      "summary": "Russian attempt to repair tunnel area sparks safe-haven procedure for five other astronauts onboard.",
      "urgency": "info",
      "topic": "general",
      "sources": [
        {
          "name": "BBC World",
          "logo": "https://www.google.com/s2/favicons?domain=bbc.com&sz=32",
          "url": "https://bbc.com/news",
          "category": "global_media"
        }
      ],
      "timestamp": "2026-06-05T16:14:36.000Z",
      "widgetType": "news",
      "link": "https://www.bbc.com/news/articles/c5y7yryg01mo?at_medium=RSS&amp;at_campaign=rss"
    },
    {
      "id": "news-50",
      "headline": "Ireland imposes travel ban on Israeli ministers Ben-Gvir and Smotrich",
      "summary": "Irish Taoiseach Martin says the ministers have shown &#039;a desire to see the elimination of Palestinians from Palestine&#039;.",
      "urgency": "info",
      "topic": "middle-east",
      "sources": [
        {
          "name": "Al Jazeera",
          "logo": "https://www.google.com/s2/favicons?domain=aljazeera.com&sz=32",
          "url": "https://aljazeera.com",
          "category": "global_media"
        }
      ],
      "timestamp": "2026-06-05T16:10:55.000Z",
      "widgetType": "news",
      "link": "https://www.aljazeera.com/news/2026/6/5/ireland-imposes-travel-ban-on-israeli-ministers-ben-gvir-and-smotrich?traffic_source=rss"
    },
    {
      "id": "news-51",
      "headline": "Why Washington is reducing visa processing across Africa",
      "summary": "US plans to centralise visa processing across Africa could increase cross-border travel for visa applicants.",
      "urgency": "info",
      "topic": "general",
      "sources": [
        {
          "name": "Al Jazeera",
          "logo": "https://www.google.com/s2/favicons?domain=aljazeera.com&sz=32",
          "url": "https://aljazeera.com",
          "category": "global_media"
        }
      ],
      "timestamp": "2026-06-05T16:10:30.000Z",
      "widgetType": "news",
      "link": "https://www.aljazeera.com/news/2026/6/5/why-washington-is-reducing-visa-processing-across-africa?traffic_source=rss"
    },
    {
      "id": "news-52",
      "headline": "Magnitude 5.0 earthquake strikes southern Iran, tremors felt across the region",
      "summary": "Magnitude 5.0 earthquake strikes southern Iran, tremors felt across the region",
      "urgency": "breaking",
      "topic": "middle-east",
      "sources": [
        {
          "name": "Gulf News",
          "logo": "https://www.google.com/s2/favicons?domain=gulfnews.com&sz=32",
          "url": "https://gulfnews.com",
          "category": "local_media"
        }
      ],
      "timestamp": "2026-06-05T16:09:34.000Z",
      "widgetType": "news",
      "link": "https://gulfnews.com/world/mena/magnitude-50-earthquake-strikes-southern-iran-tremors-felt-across-the-region-1.500564860"
    },
    {
      "id": "news-53",
      "headline": "Dubai traffic alert: RTA announces diversions from June 6",
      "summary": "Dubai traffic alert: RTA announces diversions from June 6",
      "urgency": "info",
      "topic": "general",
      "sources": [
        {
          "name": "Gulf News",
          "logo": "https://www.google.com/s2/favicons?domain=gulfnews.com&sz=32",
          "url": "https://gulfnews.com",
          "category": "local_media"
        }
      ],
      "timestamp": "2026-06-05T16:06:37.000Z",
      "widgetType": "news",
      "link": "https://gulfnews.com/uae/transport/dubai-traffic-alert-rta-announces-diversions-from-june-6-1.500564853"
    },
    {
      "id": "news-54",
      "headline": "Dubai brings Eid joy to 350,000 workers through major initiative",
      "summary": "Dubai brings Eid joy to 350,000 workers through major initiative",
      "urgency": "info",
      "topic": "general",
      "sources": [
        {
          "name": "Gulf News",
          "logo": "https://www.google.com/s2/favicons?domain=gulfnews.com&sz=32",
          "url": "https://gulfnews.com",
          "category": "local_media"
        }
      ],
      "timestamp": "2026-06-05T16:05:02.000Z",
      "widgetType": "news",
      "link": "https://gulfnews.com/uae/dubai-brings-eid-joy-to-350000-workers-through-major-initiative-1.500564793"
    },
    {
      "id": "news-55",
      "headline": "Hospitality jobs boom as US prepares for World Cup",
      "summary": "It is the third month in a row US jobs figures have beaten expectations.",
      "urgency": "info",
      "topic": "general",
      "sources": [
        {
          "name": "BBC World",
          "logo": "https://www.google.com/s2/favicons?domain=bbc.com&sz=32",
          "url": "https://bbc.com/news",
          "category": "global_media"
        }
      ],
      "timestamp": "2026-06-05T16:02:17.000Z",
      "widgetType": "news",
      "link": "https://www.bbc.com/news/articles/cdxpx4gel1yo?at_medium=RSS&amp;at_campaign=rss"
    },
    {
      "id": "news-56",
      "headline": "How Chinese drink chains are testing the limits of soft power",
      "summary": "Makeda George steps out of a Mixue store in downtown Brooklyn, New York, clutching a bubble tea as she weaves through a crowd of teenagers. The local resident says she had been eager to try the brand after noticing a surge of new outlets opening in recent months.\n“I decided to try the bubble tea. It",
      "urgency": "info",
      "topic": "general",
      "sources": [
        {
          "name": "SCMP",
          "logo": "https://www.google.com/s2/favicons?domain=scmp.com&sz=32",
          "url": "https://scmp.com",
          "category": "local_media"
        }
      ],
      "timestamp": "2026-06-05T16:01:05.000Z",
      "widgetType": "news",
      "link": "https://www.scmp.com/news/us/article/3356110/how-chinese-drink-chains-are-testing-limits-soft-power?utm_source=rss_feed"
    },
    {
      "id": "news-57",
      "headline": "Exclusive: Iran supreme leader’s adviser says talks deadlocked over $24 billion and warns of wider war - CNN",
      "summary": "&lt;a href=\"https://news.google.com/rss/articles/CBMinwFBVV95cUxQWnA5aVNZalFpYVdlWHJuSE41QUlIbGFrNkdiV1Q3RzdTekJqM2oza09hcWZZMFBUNVlGN3g4eVZUc3puNmZWNjJERWFNYTRZRkZRd2pIcVVEam5KSTFmcWxlZG93ejJONDdVMnhzcVdXblB1OTQ0eG84RG9pZ1lHTlJmTXQ1UWF1VnVmZEhZNG1paEc0anlDUlBYejBPWU0?oc=5\" target=\"_blank\"&gt;Exclus",
      "urgency": "breaking",
      "topic": "middle-east",
      "sources": [
        {
          "name": "Google News",
          "logo": "https://www.google.com/s2/favicons?domain=news.google.com&sz=32",
          "url": "https://news.google.com",
          "category": "global_media"
        }
      ],
      "timestamp": "2026-06-05T16:00:49.000Z",
      "widgetType": "news",
      "link": "https://news.google.com/rss/articles/CBMinwFBVV95cUxQWnA5aVNZalFpYVdlWHJuSE41QUlIbGFrNkdiV1Q3RzdTekJqM2oza09hcWZZMFBUNVlGN3g4eVZUc3puNmZWNjJERWFNYTRZRkZRd2pIcVVEam5KSTFmcWxlZG93ejJONDdVMnhzcVdXblB1OTQ0eG84RG9pZ1lHTlJmTXQ1UWF1VnVmZEhZNG1paEc0anlDUlBYejBPWU0?oc=5"
    },
    {
      "id": "news-58",
      "headline": "Crown Princess Mette-Marit of Norway Is Placed on Lung Transplant List",
      "summary": "News of Crown Princess Mette-Marit’s worsening condition comes as a number of scandals have plunged the royal family into a deep crisis.",
      "urgency": "important",
      "topic": "general",
      "sources": [
        {
          "name": "NY Times",
          "logo": "https://www.google.com/s2/favicons?domain=nytimes.com&sz=32",
          "url": "https://nytimes.com",
          "category": "global_media"
        }
      ],
      "timestamp": "2026-06-05T16:00:49.000Z",
      "widgetType": "news",
      "link": "https://www.nytimes.com/2026/06/05/world/europe/norway-princess-lung-transplant.html"
    },
    {
      "id": "news-59",
      "headline": "Nearly 50 people die of thirst in Sahara desert after lorry breaks down",
      "summary": "Only two survived after trekking more than 50km (30 miles) across the desert to alert the authorities.",
      "urgency": "info",
      "topic": "general",
      "sources": [
        {
          "name": "BBC World",
          "logo": "https://www.google.com/s2/favicons?domain=bbc.com&sz=32",
          "url": "https://bbc.com/news",
          "category": "global_media"
        }
      ],
      "timestamp": "2026-06-05T16:00:47.000Z",
      "widgetType": "news",
      "link": "https://www.bbc.com/news/articles/c62r2ldyejro?at_medium=RSS&amp;at_campaign=rss"
    },
    {
      "id": "news-60",
      "headline": "Everest guide survived six-day ordeal by eating chocolate and 'chewing ice'",
      "summary": "Dawa Sherpa was spotted alive by a cleaning crew as he slid slowly down the world's tallest mountain and spoke to the BBC from hospital.",
      "urgency": "info",
      "topic": "general",
      "sources": [
        {
          "name": "BBC World",
          "logo": "https://www.google.com/s2/favicons?domain=bbc.com&sz=32",
          "url": "https://bbc.com/news",
          "category": "global_media"
        }
      ],
      "timestamp": "2026-06-05T15:59:58.000Z",
      "widgetType": "news",
      "link": "https://www.bbc.com/news/articles/cn9p91295q8o?at_medium=RSS&amp;at_campaign=rss"
    },
    {
      "id": "news-61",
      "headline": "Israeli Knesset member backs settlement push in southern Syria",
      "summary": "An Israeli Knesset member has publicly backed efforts to establish Israeli settlements in southern Syria.",
      "urgency": "info",
      "topic": "middle-east",
      "sources": [
        {
          "name": "Al Jazeera",
          "logo": "https://www.google.com/s2/favicons?domain=aljazeera.com&sz=32",
          "url": "https://aljazeera.com",
          "category": "global_media"
        }
      ],
      "timestamp": "2026-06-05T15:55:13.000Z",
      "widgetType": "news",
      "link": "https://www.aljazeera.com/video/newsfeed/2026/6/5/israeli-knesset-member-backs-settlement-push-in-southern-syria?traffic_source=rss"
    },
    {
      "id": "news-62",
      "headline": "Zverev eases past Mensik in French Open semifinals, in striking distance of elusive Grand Slam title",
      "summary": "Germany's Alexander Zverev on Friday moved within one win of his first Grand Slam title by beating Czech Jakub Mensik in four sets to reach the French Open final. The second seed will face Italy's Flavio Cobolli after a 7-5, 6-2, 3-6, 6-3 victory as he chases a long-awaited crown at the majors.",
      "urgency": "info",
      "topic": "general",
      "sources": [
        {
          "name": "France 24",
          "logo": "https://www.google.com/s2/favicons?domain=france24.com&sz=32",
          "url": "https://france24.com",
          "category": "global_media"
        }
      ],
      "timestamp": "2026-06-05T15:55:11.000Z",
      "widgetType": "news",
      "link": "https://www.france24.com/en/sport/20260605-zverev-defeats-mensik-in-french-open-semifinals-and-nears-grand-slam-title"
    },
    {
      "id": "news-63",
      "headline": "Ex-wife of Dubai ruler's nephew arrested in custody dispute",
      "summary": "&lt;p&gt;The ex-wife of a nephew of Dubai’s ruler has been arrested following a long-running custody battle, prosecutors in the UAE said on Friday.&lt;/p&gt;\n&lt;p&gt;Zeynab Javadli was detained after her former husband, Sheikh Saeed bin Maktoum bin Rashid Al Maktoum, accused her of abducting their ",
      "urgency": "breaking",
      "topic": "general",
      "sources": [
        {
          "name": "Dawn",
          "logo": "https://www.google.com/s2/favicons?domain=dawn.com&sz=32",
          "url": "https://dawn.com",
          "category": "local_media"
        }
      ],
      "timestamp": "2026-06-05T15:48:09.000Z",
      "widgetType": "news",
      "link": "https://www.dawn.com/news/2005445/ex-wife-of-dubai-rulers-nephew-arrested-in-custody-dispute"
    },
    {
      "id": "news-64",
      "headline": "Dubai Humanitarian airlifts Ebola medical supplies to DR Congo",
      "summary": "Dubai Humanitarian airlifts critical medical supplies with WHO to support efforts to combat Ebola in Democratic Republic of the Congo",
      "urgency": "info",
      "topic": "general",
      "sources": [
        {
          "name": "Gulf News",
          "logo": "https://www.google.com/s2/favicons?domain=gulfnews.com&sz=32",
          "url": "https://gulfnews.com",
          "category": "local_media"
        }
      ],
      "timestamp": "2026-06-05T15:42:11.000Z",
      "widgetType": "news",
      "link": "https://gulfnews.com/uae/dubai-humanitarian-airlifts-ebola-medical-supplies-to-dr-congo-1.500564811"
    },
    {
      "id": "news-65",
      "headline": "Three jailed over heist of ancient golden helmet from Dutch museum",
      "summary": "The men are sentenced to 47 months each for stealing the 2,500-year-old Romanian Coțofenești helmet.",
      "urgency": "info",
      "topic": "general",
      "sources": [
        {
          "name": "BBC World",
          "logo": "https://www.google.com/s2/favicons?domain=bbc.com&sz=32",
          "url": "https://bbc.com/news",
          "category": "global_media"
        }
      ],
      "timestamp": "2026-06-05T15:41:28.000Z",
      "widgetType": "news",
      "link": "https://www.bbc.com/news/articles/cy020317g1no?at_medium=RSS&amp;at_campaign=rss"
    },
    {
      "id": "news-66",
      "headline": "Man City chair Al Mubarak will ‘say everything’ after verdict on finances",
      "summary": "English Premier League side Manchester City charged with 115 alleged breaches of financial rules.",
      "urgency": "info",
      "topic": "general",
      "sources": [
        {
          "name": "Al Jazeera",
          "logo": "https://www.google.com/s2/favicons?domain=aljazeera.com&sz=32",
          "url": "https://aljazeera.com",
          "category": "global_media"
        }
      ],
      "timestamp": "2026-06-05T15:39:39.000Z",
      "widgetType": "news",
      "link": "https://www.aljazeera.com/sports/2026/6/5/man-city-chair-al-mubarak-will-say-everything-after-verdict-on-finances?traffic_source=rss"
    },
    {
      "id": "news-67",
      "headline": "Hong Kong man arrested for allegedly groping schoolgirl on bus",
      "summary": "Hong Kong police have arrested a 65-year-old man in connection with a suspected indecent assault case in Mong Kok hours after footage appeared online showing a passenger harassing a schoolgirl sitting in front of him on a bus.\nPolice said officers intercepted the suspect at the boundary checkpoint o",
      "urgency": "info",
      "topic": "general",
      "sources": [
        {
          "name": "SCMP",
          "logo": "https://www.google.com/s2/favicons?domain=scmp.com&sz=32",
          "url": "https://scmp.com",
          "category": "local_media"
        }
      ],
      "timestamp": "2026-06-05T15:33:29.000Z",
      "widgetType": "news",
      "link": "https://www.scmp.com/news/hong-kong/law-and-crime/article/3356171/hong-kong-man-arrested-allegedly-groping-schoolgirl-bus?utm_source=rss_feed"
    },
    {
      "id": "news-68",
      "headline": "Bilawal vows to ensure ownership rights, 18th Amendment protections for Gilgit-Baltistan",
      "summary": "&lt;p&gt;PPP Chairman Bilawal Bhutto-Zardari on Friday promised to ensure the right of ownership and the protections of the 18th Constitutional Amendment for the people of Gilgit-Baltistan.&lt;/p&gt;\n&lt;p&gt;His remarks came during a public rally in Gilgit, part of his region-wide campaign ahead of",
      "urgency": "breaking",
      "topic": "general",
      "sources": [
        {
          "name": "Dawn",
          "logo": "https://www.google.com/s2/favicons?domain=dawn.com&sz=32",
          "url": "https://dawn.com",
          "category": "local_media"
        }
      ],
      "timestamp": "2026-06-05T15:32:23.000Z",
      "widgetType": "news",
      "link": "https://www.dawn.com/news/2005434/bilawal-vows-to-ensure-ownership-rights-18th-amendment-protections-for-gilgit-baltistan"
    },
    {
      "id": "news-69",
      "headline": "Fall in official Ebola numbers appears to be good news but it's not that simple",
      "summary": "There are now 380 confirmed cases of Ebola in DR Congo, far lower than initial estimates of suspected cases, writes Fergus Walsh.",
      "urgency": "info",
      "topic": "general",
      "sources": [
        {
          "name": "BBC Africa",
          "logo": "https://www.google.com/s2/favicons?domain=bbc.com&sz=32",
          "url": "https://bbc.com/news",
          "category": "global_media"
        }
      ],
      "timestamp": "2026-06-05T15:30:08.000Z",
      "widgetType": "news",
      "link": "https://www.bbc.com/news/articles/c0q2q4y09elo?at_medium=RSS&amp;at_campaign=rss"
    },
    {
      "id": "news-70",
      "headline": "FIFA ups payments to clubs who send players to World Cup",
      "summary": "FIFA ups payments to clubs who send players to World Cup",
      "urgency": "info",
      "topic": "general",
      "sources": [
        {
          "name": "Gulf News",
          "logo": "https://www.google.com/s2/favicons?domain=gulfnews.com&sz=32",
          "url": "https://gulfnews.com",
          "category": "local_media"
        }
      ],
      "timestamp": "2026-06-05T15:30:04.000Z",
      "widgetType": "news",
      "link": "https://gulfnews.com/sport/football/world-cup/fifa-ups-payments-to-clubs-who-send-players-to-world-cup-3-1.500564817"
    },
    {
      "id": "news-71",
      "headline": "Ukraine strikes cargo ships and admits Romania drone blast",
      "summary": "Ukraine says it struck five ships carrying illegal cargo in the Sea of Azov and in coastal waters of Russian-occupied territories.",
      "urgency": "breaking",
      "topic": "ukraine-russia",
      "sources": [
        {
          "name": "BBC World",
          "logo": "https://www.google.com/s2/favicons?domain=bbc.com&sz=32",
          "url": "https://bbc.com/news",
          "category": "global_media"
        }
      ],
      "timestamp": "2026-06-05T15:29:39.000Z",
      "widgetType": "news",
      "link": "https://www.bbc.com/news/articles/c707098wkzpo?at_medium=RSS&amp;at_campaign=rss"
    },
    {
      "id": "news-72",
      "headline": "‘Red meat is a dream’: Iran inflation hits highest level since World War II",
      "summary": "The war with the US is not the only factor driving prices skywards.",
      "urgency": "breaking",
      "topic": "middle-east",
      "sources": [
        {
          "name": "Al Jazeera",
          "logo": "https://www.google.com/s2/favicons?domain=aljazeera.com&sz=32",
          "url": "https://aljazeera.com",
          "category": "global_media"
        }
      ],
      "timestamp": "2026-06-05T15:28:49.000Z",
      "widgetType": "news",
      "link": "https://www.aljazeera.com/news/2026/6/5/red-meat-is-a-dream-iran-inflation-hits-highest-level-since-world-war-ii?traffic_source=rss"
    },
    {
      "id": "news-73",
      "headline": "UK’s Keir Starmer says Russia could attack Nato within 4 years",
      "summary": "Russia could attack a Nato country within four years according to western intelligence assessments, UK Prime Minister Keir Starmer warned on Friday.\nHe made the comments as he pledged his government would publish a long-delayed defence investment plan before next month’s Nato summit.\n“It is our inte",
      "urgency": "breaking",
      "topic": "general",
      "sources": [
        {
          "name": "SCMP",
          "logo": "https://www.google.com/s2/favicons?domain=scmp.com&sz=32",
          "url": "https://scmp.com",
          "category": "local_media"
        }
      ],
      "timestamp": "2026-06-05T15:25:59.000Z",
      "widgetType": "news",
      "link": "https://www.scmp.com/news/world/europe/article/3356170/uks-keir-starmer-says-russia-could-attack-nato-within-4-years?utm_source=rss_feed"
    },
    {
      "id": "news-74",
      "headline": "At least 49 people die of thirst after truck breakdown in Niger desert",
      "summary": "Two people managed to survive after walking more than 50km to a water source and then a nearby town.",
      "urgency": "info",
      "topic": "general",
      "sources": [
        {
          "name": "Al Jazeera",
          "logo": "https://www.google.com/s2/favicons?domain=aljazeera.com&sz=32",
          "url": "https://aljazeera.com",
          "category": "global_media"
        }
      ],
      "timestamp": "2026-06-05T15:17:14.000Z",
      "widgetType": "news",
      "link": "https://www.aljazeera.com/news/2026/6/5/at-least-49-people-die-of-thirst-after-truck-breakdown-in-niger-desert?traffic_source=rss"
    },
    {
      "id": "news-75",
      "headline": "Unicorn in the USA: Indians aren't stealing American jobs; they are building entire HR departments",
      "summary": "&lt;img border=\"0\" hspace=\"10\" align=\"left\" style=\"margin-top:3px;margin-right:5px;\" src=\"https://timesofindia.indiatimes.com/photo/131535094.cms\" /&gt;<![CDATA[Immigrants are driving America's innovation, founding 59% of billion-dollar startups, known as unicorns. People of Indian origin lead this ",
      "urgency": "important",
      "topic": "general",
      "sources": [
        {
          "name": "Times of India",
          "logo": "https://www.google.com/s2/favicons?domain=timesofindia.indiatimes.com&sz=32",
          "url": "https://timesofindia.indiatimes.com",
          "category": "local_media"
        }
      ],
      "timestamp": "2026-06-05T15:15:11.000Z",
      "widgetType": "news",
      "link": "https://timesofindia.indiatimes.com/world/us/unicorn-in-the-usa-indians-arent-stealing-american-jobs-they-are-building-entire-hr-departments/articleshow/131535094.cms"
    },
    {
      "id": "news-76",
      "headline": "What is Ebola and why is stopping the latest outbreak so difficult?",
      "summary": "An outbreak of Ebola in DR Congo involves a rare species of the virus and is in an area affected by conflict.",
      "urgency": "info",
      "topic": "general",
      "sources": [
        {
          "name": "BBC Africa",
          "logo": "https://www.google.com/s2/favicons?domain=bbc.com&sz=32",
          "url": "https://bbc.com/news",
          "category": "global_media"
        }
      ],
      "timestamp": "2026-06-05T15:14:22.000Z",
      "widgetType": "news",
      "link": "https://www.bbc.com/news/articles/cz72p75zg4qo?at_medium=RSS&amp;at_campaign=rss"
    },
    {
      "id": "news-77",
      "headline": "The Gold Mines at the Heart of This Ebola Outbreak",
      "summary": "Mining has been the lifeblood of this remote Congolese hill town for decades. Now, it is fueling the spread of a devastating virus.",
      "urgency": "info",
      "topic": "general",
      "sources": [
        {
          "name": "NY Times",
          "logo": "https://www.google.com/s2/favicons?domain=nytimes.com&sz=32",
          "url": "https://nytimes.com",
          "category": "global_media"
        }
      ],
      "timestamp": "2026-06-05T15:13:35.000Z",
      "widgetType": "news",
      "link": "https://www.nytimes.com/2026/06/05/world/africa/congo-ebola-gold-mine.html"
    },
    {
      "id": "news-78",
      "headline": "Holocaust remembrance: Newly discovered photos illustrate previously-unknown roundup of French Jews",
      "summary": "François Picard is pleased to welcome Dr. Jean-Marc Dreyfus, Historian, Professor of Modern History at the University of Manchester, Chief Editor of 'La Revue d'Histoire de la Shoah' and one of the curators of the Shoah Memorial in Paris photography exhibit highlighting the discovery of 98 previousl",
      "urgency": "info",
      "topic": "general",
      "sources": [
        {
          "name": "France 24",
          "logo": "https://www.google.com/s2/favicons?domain=france24.com&sz=32",
          "url": "https://france24.com",
          "category": "global_media"
        }
      ],
      "timestamp": "2026-06-05T15:11:05.000Z",
      "widgetType": "news",
      "link": "https://www.france24.com/en/tv-shows/spotlight/20260605-holocaust-remembrance-newly-discovered-photos-illustrate-previously-unknown-roundup-of-french-jews"
    },
    {
      "id": "news-79",
      "headline": "Ukrainian drone explodes in Romanian sea port",
      "summary": "A sea #drone self-destroyed in the Romanian port of Constanta. #Ukraine's navy said it had been knocked off course by Russian jamming.",
      "urgency": "info",
      "topic": "general",
      "sources": [
        {
          "name": "France 24",
          "logo": "https://www.google.com/s2/favicons?domain=france24.com&sz=32",
          "url": "https://france24.com",
          "category": "global_media"
        }
      ],
      "timestamp": "2026-06-05T15:09:00.000Z",
      "widgetType": "news",
      "link": "https://www.france24.com/en/video/20260605-ukrainian-drone-explodes-in-romanian-sea-port"
    },
    {
      "id": "news-80",
      "headline": "Barcelona teenager Lamine Yamal wins La Liga Player of the Season award",
      "summary": "Lamine Yamal will be an integral part of Spain&#039;s World Cup 2026 challenge and was key in Barcelona&#039;s La Liga defence.",
      "urgency": "breaking",
      "topic": "general",
      "sources": [
        {
          "name": "Al Jazeera",
          "logo": "https://www.google.com/s2/favicons?domain=aljazeera.com&sz=32",
          "url": "https://aljazeera.com",
          "category": "global_media"
        }
      ],
      "timestamp": "2026-06-05T15:05:25.000Z",
      "widgetType": "news",
      "link": "https://www.aljazeera.com/sports/2026/6/5/barcelona-teenager-lamine-yamal-wins-la-liga-player-of-season-award?traffic_source=rss"
    },
    {
      "id": "news-81",
      "headline": "NASA places ISS astronauts on evacuation alert as air leak worsens",
      "summary": "NASA places ISS astronauts on evacuation alert as air leak worsens",
      "urgency": "info",
      "topic": "general",
      "sources": [
        {
          "name": "France 24",
          "logo": "https://www.google.com/s2/favicons?domain=france24.com&sz=32",
          "url": "https://france24.com",
          "category": "global_media"
        }
      ],
      "timestamp": "2026-06-05T15:01:13.000Z",
      "widgetType": "news",
      "link": "https://www.france24.com/en/science/20260605-nasa-places-iss-astronauts-on-evacuation-alert-as-air-leak-worsens"
    },
    {
      "id": "news-82",
      "headline": "Everest Sherpa, who was presumed dead, found alive after 6 days; family demands probe into rescue delays",
      "summary": "&lt;p&gt;The family of a Nepali climber who dragged himself off Mount Everest six days after being abandoned called for an investigation into rescue efforts, as doctors said on Friday he is in a stable condition and recovering in hospital.&lt;/p&gt;\n&lt;p&gt;Mountaineer Dawa Sherpa, 57, vanished in ",
      "urgency": "breaking",
      "topic": "general",
      "sources": [
        {
          "name": "Dawn",
          "logo": "https://www.google.com/s2/favicons?domain=dawn.com&sz=32",
          "url": "https://dawn.com",
          "category": "local_media"
        }
      ],
      "timestamp": "2026-06-05T15:00:45.000Z",
      "widgetType": "news",
      "link": "https://www.dawn.com/news/2005411/everest-sherpa-who-was-presumed-dead-found-alive-after-6-days-family-demands-probe-into-rescue-delays"
    },
    {
      "id": "news-83",
      "headline": "Australian housing was already cooling before the budget – but how cold it gets depends on two key factors",
      "summary": "&lt;p&gt;Most economists believe the chronic undersupply of homes will eventually push prices higher once interest rates ease and the tax changes are priced in&lt;/p&gt;&lt;ul&gt;&lt;li&gt;&lt;p&gt;Get our &lt;a href=\"https://www.theguardian.com/email-newsletters?CMP=cvau_sfl\"&gt;breaking news email",
      "urgency": "breaking",
      "topic": "general",
      "sources": [
        {
          "name": "The Guardian",
          "logo": "https://www.google.com/s2/favicons?domain=theguardian.com&sz=32",
          "url": "https://theguardian.com",
          "category": "global_media"
        }
      ],
      "timestamp": "2026-06-05T15:00:04.000Z",
      "widgetType": "news",
      "link": "https://www.theguardian.com/australia-news/2026/jun/06/australia-housing-house-prices-supply-before-budget-after-cgt-capital-gains-tax-negative-gearing-changes"
    },
    {
      "id": "news-84",
      "headline": "FRANCE 24 journalists forced to sign NDA after asking about open letter against media mogul Bolloré",
      "summary": "Two FRANCE 24 journalists were forced to sign a non-disclosure agreement after asking an actor about an open letter protesting the growing role of far-right billionaire Vincent Bolloré in French cinema. Signed by hundreds of industry professionals, the letter prompted the head of the Canal+ Group – ",
      "urgency": "important",
      "topic": "general",
      "sources": [
        {
          "name": "France 24",
          "logo": "https://www.google.com/s2/favicons?domain=france24.com&sz=32",
          "url": "https://france24.com",
          "category": "global_media"
        }
      ],
      "timestamp": "2026-06-05T14:59:55.000Z",
      "widgetType": "news",
      "link": "https://www.france24.com/en/france/20260605-france-24-journalists-forced-to-sign-nda-after-asking-about-open-letter-against-media-mogul-bollor%C3%A9"
    },
    {
      "id": "news-85",
      "headline": "Saudi Arabia launches new Jeddah–India shipping link to boost trade flows",
      "summary": "&lt;img border=\"0\" hspace=\"10\" align=\"left\" style=\"margin-top:3px;margin-right:5px;\" src=\"https://timesofindia.indiatimes.com/photo/131534897.cms\" /&gt;<![CDATA[",
      "urgency": "info",
      "topic": "general",
      "sources": [
        {
          "name": "Times of India",
          "logo": "https://www.google.com/s2/favicons?domain=timesofindia.indiatimes.com&sz=32",
          "url": "https://timesofindia.indiatimes.com",
          "category": "local_media"
        }
      ],
      "timestamp": "2026-06-05T14:59:41.000Z",
      "widgetType": "news",
      "link": "https://timesofindia.indiatimes.com/world/middle-east/indias-mundra-port-linked-to-saudi-arabias-jeddah-in-new-red-sea-shipping-route/articleshow/131534897.cms"
    },
    {
      "id": "news-86",
      "headline": "AJK govt issues travel advisory ahead of JAAC protest, asks visitors to leave",
      "summary": "&lt;p&gt;MUZAFFARABAD: The Azad Jammu and Kashmir (AJK) government on Friday urged outsiders to avoid travelling to the region and asked current visitors to leave immediately, ahead of a &lt;a href=\"https://www.dawn.com/news/2004054\"&gt;major protest&lt;/a&gt; that has prompted the deployment of fed",
      "urgency": "breaking",
      "topic": "general",
      "sources": [
        {
          "name": "Dawn",
          "logo": "https://www.google.com/s2/favicons?domain=dawn.com&sz=32",
          "url": "https://dawn.com",
          "category": "local_media"
        }
      ],
      "timestamp": "2026-06-05T14:59:15.000Z",
      "widgetType": "news",
      "link": "https://www.dawn.com/news/2005432/ajk-govt-issues-travel-advisory-ahead-of-jaac-protest-asks-visitors-to-leave"
    },
    {
      "id": "news-87",
      "headline": "Hong Kong ideal platform for Uzbek firms to spread wings globally, John Lee says",
      "summary": "Hong Kong serves as an ideal platform to help Uzbek enterprises expand through its world-class professional services and international business environment, the city’s leader has told the Central Asian country’s prime minister as he wrapped up a five-day regional tour.\nSources said Chief Executive J",
      "urgency": "important",
      "topic": "general",
      "sources": [
        {
          "name": "SCMP",
          "logo": "https://www.google.com/s2/favicons?domain=scmp.com&sz=32",
          "url": "https://scmp.com",
          "category": "local_media"
        }
      ],
      "timestamp": "2026-06-05T14:59:03.000Z",
      "widgetType": "news",
      "link": "https://www.scmp.com/news/hong-kong/hong-kong-economy/article/3356166/hong-kong-ideal-platform-uzbek-firms-spread-wings-globally-john-lee-says?utm_source=rss_feed"
    },
    {
      "id": "news-88",
      "headline": "YouTubers face backlash for terminating pregnancy after learning child had Down syndrome",
      "summary": "&lt;img border=\"0\" hspace=\"10\" align=\"left\" style=\"margin-top:3px;margin-right:5px;\" src=\"https://timesofindia.indiatimes.com/photo/131533963.cms\" /&gt;<![CDATA[",
      "urgency": "info",
      "topic": "general",
      "sources": [
        {
          "name": "Times of India",
          "logo": "https://www.google.com/s2/favicons?domain=timesofindia.indiatimes.com&sz=32",
          "url": "https://timesofindia.indiatimes.com",
          "category": "local_media"
        }
      ],
      "timestamp": "2026-06-05T14:58:26.000Z",
      "widgetType": "news",
      "link": "https://timesofindia.indiatimes.com/world/us/compared-to-hitler-youtuber-couple-faces-backlash-for-terminating-pregnancy-after-learning-unborn-child-had-down-syndrome/articleshow/131533963.cms"
    },
    {
      "id": "news-89",
      "headline": "Hopes of Lebanon Cease-Fire Falter as Israel and Hezbollah Fight On",
      "summary": "The U.S.-brokered agreement requires Hezbollah, which Iran backs, to stop firing first. But the group, not party to the talks, rejected the conditions as a virtual surrender.",
      "urgency": "info",
      "topic": "middle-east",
      "sources": [
        {
          "name": "NY Times",
          "logo": "https://www.google.com/s2/favicons?domain=nytimes.com&sz=32",
          "url": "https://nytimes.com",
          "category": "global_media"
        }
      ],
      "timestamp": "2026-06-05T14:56:02.000Z",
      "widgetType": "news",
      "link": "https://www.nytimes.com/2026/06/05/world/middleeast/lebanon-cease-fire-israel-hezbollah.html"
    },
    {
      "id": "news-90",
      "headline": "WHO, Africa CDC unveil $518m Ebola plan as Uganda death toll rises",
      "summary": "Uganda reported three more cases and one more death from the outbreak which has spread from the DRC.",
      "urgency": "info",
      "topic": "general",
      "sources": [
        {
          "name": "Al Jazeera",
          "logo": "https://www.google.com/s2/favicons?domain=aljazeera.com&sz=32",
          "url": "https://aljazeera.com",
          "category": "global_media"
        }
      ],
      "timestamp": "2026-06-05T14:52:36.000Z",
      "widgetType": "news",
      "link": "https://www.aljazeera.com/news/2026/6/5/who-africa-cdc-unveil-518m-ebola-plan-as-uganda-death-toll-rises?traffic_source=rss"
    },
    {
      "id": "news-91",
      "headline": "ISS astronauts briefly put on evacuation alert during repair to fix air leak",
      "summary": "NASA ordered astronauts aboard the International Space Station (ISS) to shelter in their spacecraft and prepare for a possible evacuation on Friday after an air leak in the Russian module of the orbiting laboratory worsened, raising fresh concerns over a long-running technical problem.",
      "urgency": "info",
      "topic": "general",
      "sources": [
        {
          "name": "France 24",
          "logo": "https://www.google.com/s2/favicons?domain=france24.com&sz=32",
          "url": "https://france24.com",
          "category": "global_media"
        }
      ],
      "timestamp": "2026-06-05T14:50:49.000Z",
      "widgetType": "news",
      "link": "https://www.france24.com/en/science/20260605-nasa-places-iss-astronauts-on-evacuation-alert-as-air-leak-worsens"
    },
    {
      "id": "news-92",
      "headline": "France opens torture, 'war crime' probe over Israel's treatment of Gaza flotilla activists",
      "summary": "France opens torture, 'war crime' probe over Israel's treatment of Gaza flotilla activists",
      "urgency": "breaking",
      "topic": "middle-east",
      "sources": [
        {
          "name": "France 24",
          "logo": "https://www.google.com/s2/favicons?domain=france24.com&sz=32",
          "url": "https://france24.com",
          "category": "global_media"
        }
      ],
      "timestamp": "2026-06-05T14:43:21.000Z",
      "widgetType": "news",
      "link": "https://www.france24.com/en/middle-east/20260605-france-opens-torture-war-crime-probe-over-israel-s-treatment-of-gaza-flotilla-activists"
    },
    {
      "id": "news-93",
      "headline": "WFP: War on Iran pushing millions towards hunger",
      "summary": "The US-Israeli war on Iran could tip up to 45 million people into acute hunger, the UN&#039;s WFP warns.",
      "urgency": "breaking",
      "topic": "middle-east",
      "sources": [
        {
          "name": "Al Jazeera",
          "logo": "https://www.google.com/s2/favicons?domain=aljazeera.com&sz=32",
          "url": "https://aljazeera.com",
          "category": "global_media"
        }
      ],
      "timestamp": "2026-06-05T14:41:54.000Z",
      "widgetType": "news",
      "link": "https://www.aljazeera.com/video/newsfeed/2026/6/5/wfp-war-on-iran-pushing-millions-towards-hunger?traffic_source=rss"
    },
    {
      "id": "news-94",
      "headline": "Are the US and Iran closer to war or to a deal? - Al Jazeera",
      "summary": "&lt;a href=\"https://news.google.com/rss/articles/CBMiigFBVV95cUxOVVhJRkhSSnYzdi1PZVk5NHp1LUEtRWN4UW5kb0NIVnI2UjZ3MlRwT3hvRUxyZ1o5X052WUVZUEFRNGZabm5SSmFVVDBwMjdUeXZfSzhtMXB1QXluaHNkbGtEQUx0UnF6ZHpSZGhLcU1xTDBqT2R5Z3pqc0FTYVU0bUNkTzY2bDZzdVHSAY8BQVVfeXFMUEdJc25ldVFVT1J6cW5fMlp0b1h1cHA0cUgwV0lDN04xMTJ",
      "urgency": "breaking",
      "topic": "middle-east",
      "sources": [
        {
          "name": "Google News",
          "logo": "https://www.google.com/s2/favicons?domain=news.google.com&sz=32",
          "url": "https://news.google.com",
          "category": "global_media"
        }
      ],
      "timestamp": "2026-06-05T14:37:51.000Z",
      "widgetType": "news",
      "link": "https://news.google.com/rss/articles/CBMiigFBVV95cUxOVVhJRkhSSnYzdi1PZVk5NHp1LUEtRWN4UW5kb0NIVnI2UjZ3MlRwT3hvRUxyZ1o5X052WUVZUEFRNGZabm5SSmFVVDBwMjdUeXZfSzhtMXB1QXluaHNkbGtEQUx0UnF6ZHpSZGhLcU1xTDBqT2R5Z3pqc0FTYVU0bUNkTzY2bDZzdVHSAY8BQVVfeXFMUEdJc25ldVFVT1J6cW5fMlp0b1h1cHA0cUgwV0lDN04xMTJ4djg1QkJhanhNQmwxU0JMbUxHQ0NXS2ZwMlFhajk5dkQ3WFNlWVZ5RVBWdEFKN1ZOM25mZDB3eTV4d0NyLUE4SXdfX3BFWGp6VWd2TTJzeVJmXzF3cGZwWE5CUmphZVJFc2ZwVHM?oc=5"
    },
    {
      "id": "news-95",
      "headline": "Why Zelensky's letter wasn't about Putin as Kremlin rejects meeting - The Kyiv Independent",
      "summary": "&lt;a href=\"https://news.google.com/rss/articles/CBMibkFVX3lxTE10bjBsVENhV0JSTXphN2JoQmxLV25GdTBjbnFzc0Z2WEE4QkZKaWdnSXM2VGJvTW9EWnB2WEI2UnBUN2I1eVZ6SzFZdDd1a0V1eWloSlIwY3dhVlZYZEN0ZFlSYkZ6Z1F1N2pybi1B?oc=5\" target=\"_blank\"&gt;Why Zelensky's letter wasn't about Putin as Kremlin rejects meeting&lt;/a",
      "urgency": "info",
      "topic": "ukraine-russia",
      "sources": [
        {
          "name": "Kyiv Independent",
          "logo": "https://www.google.com/s2/favicons?domain=kyivindependent.com&sz=32",
          "url": "https://kyivindependent.com",
          "category": "local_media"
        }
      ],
      "timestamp": "2026-06-05T14:33:57.000Z",
      "widgetType": "news",
      "link": "https://news.google.com/rss/articles/CBMibkFVX3lxTE10bjBsVENhV0JSTXphN2JoQmxLV25GdTBjbnFzc0Z2WEE4QkZKaWdnSXM2VGJvTW9EWnB2WEI2UnBUN2I1eVZ6SzFZdDd1a0V1eWloSlIwY3dhVlZYZEN0ZFlSYkZ6Z1F1N2pybi1B?oc=5"
    },
    {
      "id": "news-96",
      "headline": "Russia Floods Armenia With Disinformation Ahead of Election",
      "summary": "Fearing a loss of influence, groups linked to the Kremlin and intelligence agencies have sought to discredit the country’s prime minister.",
      "urgency": "important",
      "topic": "general",
      "sources": [
        {
          "name": "NY Times",
          "logo": "https://www.google.com/s2/favicons?domain=nytimes.com&sz=32",
          "url": "https://nytimes.com",
          "category": "global_media"
        }
      ],
      "timestamp": "2026-06-05T14:33:43.000Z",
      "widgetType": "news",
      "link": "https://www.nytimes.com/2026/06/05/world/europe/armenia-election-russia-disinformation.html"
    },
    {
      "id": "news-97",
      "headline": "New rule for work permit in US: Asylum seekers may lose jobs under DHS proposal",
      "summary": "&lt;img border=\"0\" hspace=\"10\" align=\"left\" style=\"margin-top:3px;margin-right:5px;\" src=\"https://timesofindia.indiatimes.com/photo/131534329.cms\" /&gt;<![CDATA[",
      "urgency": "info",
      "topic": "general",
      "sources": [
        {
          "name": "Times of India",
          "logo": "https://www.google.com/s2/favicons?domain=timesofindia.indiatimes.com&sz=32",
          "url": "https://timesofindia.indiatimes.com",
          "category": "local_media"
        }
      ],
      "timestamp": "2026-06-05T14:28:12.000Z",
      "widgetType": "news",
      "link": "https://timesofindia.indiatimes.com/world/us/new-rule-for-work-permit-in-us-asylum-seekers-may-lose-jobs-under-proposed-dhs-rule/articleshow/131534329.cms"
    },
    {
      "id": "news-98",
      "headline": "Doubts grow over future of '60 Minutes' after firing of Scott Pelley",
      "summary": "Turmoil continues at CBS News. As bosses defend the firing of longtime \"60 Minutes\" correspondent Scott Pelley, many journalists are questioning the network's strategy. Newsroom shake-ups usually occur at failing programmes, but \"60 Minutes\" has led ratings for years, if not decades. This week's gue",
      "urgency": "info",
      "topic": "general",
      "sources": [
        {
          "name": "France 24",
          "logo": "https://www.google.com/s2/favicons?domain=france24.com&sz=32",
          "url": "https://france24.com",
          "category": "global_media"
        }
      ],
      "timestamp": "2026-06-05T14:26:23.000Z",
      "widgetType": "news",
      "link": "https://www.france24.com/en/tv-shows/scoop/20260605-doubts-grow-over-future-of-60-minutes-after-firing-of-scott-pelley"
    },
    {
      "id": "news-99",
      "headline": "Most Asia-Pacific firms use AI for tasks without cutting jobs: survey",
      "summary": "While a wave of job cuts across Asia’s finance and other industries due to wider use of artificial intelligence has spurred concerns, a new study shows that the technology’s net impact on employment is not as clear-cut.\nRecruiters and industry observers say many companies are adding AI-related roles",
      "urgency": "info",
      "topic": "general",
      "sources": [
        {
          "name": "SCMP",
          "logo": "https://www.google.com/s2/favicons?domain=scmp.com&sz=32",
          "url": "https://scmp.com",
          "category": "local_media"
        }
      ],
      "timestamp": "2026-06-05T14:16:15.000Z",
      "widgetType": "news",
      "link": "https://www.scmp.com/week-asia/economics/article/3356163/most-asia-pacific-firms-use-ai-tasks-without-cutting-jobs-survey?utm_source=rss_feed"
    }
  ],
  "financials": {
    "exchangeRates": {
      "USD": 1,
      "AED": 3.6725,
      "SAR": 3.75,
      "GBP": 0.744474,
      "INR": 95.841716,
      "JPY": 159.95253,
      "EUR": 0.860529,
      "PKR": 278.636652,
      "EGP": 51.820284,
      "TRY": 46.03504,
      "CAD": 1.389906,
      "AUD": 1.401303,
      "BRL": 5.064065,
      "ZAR": 16.297778,
      "NGN": 1360.607362,
      "KES": 129.257225,
      "JOD": 0.709,
      "LBP": 89500,
      "IQD": 1310.178671,
      "QAR": 3.64,
      "KWD": 0.308241,
      "BHD": 0.376,
      "OMR": 0.384497,
      "ILS": 2.892821,
      "KRW": 1532.415441
    },
    "gold": {
      "label": "Gold (USD/oz)",
      "value": 2650,
      "change": 12.5,
      "changePercent": 0.47
    },
    "oil": {
      "label": "Brent Crude (USD)",
      "value": 73.5,
      "change": -0.45,
      "changePercent": -0.61
    }
  }
}